pynumdiff/README.md
pynumdiff/__init__.py
pynumdiff/_version.py
pynumdiff/basis_fit.py
pynumdiff/finite_difference.py
pynumdiff/kalman_smooth.py
pynumdiff/linear_model.py
pynumdiff/optimize.py
pynumdiff/polynomial_fit.py
pynumdiff/smooth_finite_difference.py
pynumdiff/total_variation_regularization.py
pynumdiff/tests/__init__.py
pynumdiff/tests/conftest.py
pynumdiff/tests/test_diff_methods.py
pynumdiff/tests/test_optimize.py
pynumdiff/tests/test_utils.py
pynumdiff/utils/__init__.py
pynumdiff/utils/_chartrand_tvregdiff.py
pynumdiff/utils/evaluate.py
pynumdiff/utils/old_pi_cruise_control.py
pynumdiff/utils/simulate.py
pynumdiff/utils/utility.py
pynumdiff-0.2.1.dist-info/licenses/LICENSE.txt
pynumdiff-0.2.1.dist-info/METADATA
pynumdiff-0.2.1.dist-info/WHEEL
pynumdiff-0.2.1.dist-info/top_level.txt
pynumdiff-0.2.1.dist-info/RECORD
