Metadata-Version: 2.4
Name: pynumdiff
Version: 0.2.1
Summary: pynumdiff: numerical derivatives in python
Maintainer-email: Floris van Breugel <fvanbreugel@unr.edu>, Pavel Komarov <pvlkmrv@uw.edu>, Yuying Liu <yliu814@uw.edu>
License-Expression: MIT
Project-URL: homepage, https://github.com/florisvb/PyNumDiff
Project-URL: documentation, https://pynumdiff.readthedocs.io/
Project-URL: package, https://pypi.org/project/pynumdiff/
Keywords: derivative,smoothing,curve fitting,optimization,total variation
Classifier: Development Status :: 3 - Alpha
Classifier: Environment :: Console
Classifier: Intended Audience :: Science/Research
Classifier: Operating System :: OS Independent
Classifier: Programming Language :: Python
Classifier: Topic :: Scientific/Engineering
License-File: LICENSE.txt
Requires-Dist: numpy
Requires-Dist: scipy
Requires-Dist: matplotlib
Provides-Extra: advanced
Requires-Dist: cvxpy; extra == "advanced"
Requires-Dist: tqdm; extra == "advanced"
Provides-Extra: dev
Requires-Dist: pylint; extra == "dev"
Requires-Dist: pytest; extra == "dev"
Requires-Dist: cvxopt; extra == "dev"
Requires-Dist: cvxpy; extra == "dev"
Provides-Extra: docs
Requires-Dist: sphinx; extra == "docs"
Requires-Dist: sphinx_rtd_theme; extra == "docs"
Requires-Dist: myst-parser; extra == "docs"
Requires-Dist: cvxpy; extra == "docs"
Requires-Dist: tqdm; extra == "docs"
Dynamic: license-file
